README.md
setup.py
laserfiche_api/__init__.py
laserfiche_api/api_client.py
laserfiche_api/configuration.py
laserfiche_api/rest.py
laserfiche_api.egg-info/PKG-INFO
laserfiche_api.egg-info/SOURCES.txt
laserfiche_api.egg-info/dependency_links.txt
laserfiche_api.egg-info/requires.txt
laserfiche_api.egg-info/top_level.txt
laserfiche_api/api/__init__.py
laserfiche_api/api/attributes_api.py
laserfiche_api/api/audit_reasons_api.py
laserfiche_api/api/entries_api.py
laserfiche_api/api/field_definitions_api.py
laserfiche_api/api/link_definitions_api.py
laserfiche_api/api/repositories_api.py
laserfiche_api/api/searches_api.py
laserfiche_api/api/simple_searches_api.py
laserfiche_api/api/tag_definitions_api.py
laserfiche_api/api/tasks_api.py
laserfiche_api/api/template_definitions_api.py
laserfiche_api/models/__init__.py
laserfiche_api/models/attribute.py
laserfiche_api/models/attribute_collection_response.py
laserfiche_api/models/audit_event_type.py
laserfiche_api/models/audit_reason.py
laserfiche_api/models/audit_reason_collection_response.py
laserfiche_api/models/cancel_task_result.py
laserfiche_api/models/cancel_tasks_response.py
laserfiche_api/models/copy_entry_request.py
laserfiche_api/models/create_entry_request.py
laserfiche_api/models/create_entry_request_entry_type.py
laserfiche_api/models/create_multipart_upload_urls_request.py
laserfiche_api/models/create_multipart_upload_urls_response.py
laserfiche_api/models/document.py
laserfiche_api/models/entry.py
laserfiche_api/models/entry_collection_response.py
laserfiche_api/models/entry_type.py
laserfiche_api/models/export_entry_request.py
laserfiche_api/models/export_entry_request_image_format.py
laserfiche_api/models/export_entry_request_image_options.py
laserfiche_api/models/export_entry_request_part.py
laserfiche_api/models/export_entry_request_text_options.py
laserfiche_api/models/export_entry_request_watermark.py
laserfiche_api/models/export_entry_response.py
laserfiche_api/models/field.py
laserfiche_api/models/field_collection_response.py
laserfiche_api/models/field_definition.py
laserfiche_api/models/field_definition_collection_response.py
laserfiche_api/models/field_format.py
