Metadata-Version: 2.1
Name: laserfiche-api
Version: 1.1.0
Summary: Laserfiche API
Home-page: https://github.com/Layer8Err/laserfiche_api/
Author-email: 
License: UNKNOWN
Keywords: Swagger,Laserfiche API
Platform: UNKNOWN
